pymonetdb/__init__.py
pymonetdb/control.py
pymonetdb/exceptions.py
pymonetdb/mapi.py
pymonetdb/policy.py
pymonetdb/profiler.py
pymonetdb/py.typed
pymonetdb/target.py
pymonetdb/filetransfer/__init__.py
pymonetdb/filetransfer/directoryhandler.py
pymonetdb/filetransfer/downloads.py
pymonetdb/filetransfer/uploads.py
pymonetdb/sql/__init__.py
pymonetdb/sql/connections.py
pymonetdb/sql/cursors.py
pymonetdb/sql/debug.py
pymonetdb/sql/monetize.py
pymonetdb/sql/pythonize.py
pymonetdb/sql/pythonizebin.py
pymonetdb/sql/types.py
tests/__init__.py
tests/test_capabilities.py
tests/test_clientinfo.py
tests/test_connect.py
tests/test_connect_timeout.py
tests/test_contextmanager.py
tests/test_control.py
tests/test_dbapi2.py
tests/test_exceptions.py
tests/test_execute.py
tests/test_filetransfer.py
tests/test_mapi.py
tests/test_mapi_uri.py
tests/test_monetize.py
tests/test_multiline.py
tests/test_namedparams.py
tests/test_namedtuple.py
tests/test_oid.py
tests/test_policy.py
tests/test_prepare.py
tests/test_profiler.py
tests/test_pythonize.py
tests/test_resultset.py
tests/test_target.py
tests/test_temporal.py
tests/test_tls.py
tests/test_udf.py
tests/test_unicode.py
tests/timeout_helper.py
tests/util.py
tests/windows_tests.py
pymonetdb-1.9.0.dist-info/LICENSE
pymonetdb-1.9.0.dist-info/METADATA
pymonetdb-1.9.0.dist-info/WHEEL
pymonetdb-1.9.0.dist-info/top_level.txt
pymonetdb-1.9.0.dist-info/RECORD
