Metadata-Version: 2.1
Name: pymonetdb
Version: 1.9.0
Summary: Native MonetDB client Python API
Home-page: http://www.monetdb.org/
Download-URL: https://github.com/MonetDB/pymonetdb
Author: MonetDB BV
Author-email: info@monetdb.org
Classifier: Topic :: Database
Classifier: Topic :: Database :: Database Engines/Servers
Classifier: Development Status :: 5 - Production/Stable
Classifier: Intended Audience :: Developers
Classifier: License :: OSI Approved :: Mozilla Public License 2.0 (MPL 2.0)
Classifier: Programming Language :: Python :: 3
Classifier: Programming Language :: Python :: 3.7
Classifier: Programming Language :: Python :: 3.8
Classifier: Programming Language :: Python :: 3.9
Classifier: Programming Language :: Python :: 3.10
Classifier: Programming Language :: Python :: 3.11
Classifier: Programming Language :: Python :: 3.12
Classifier: Programming Language :: Python :: 3.13
Classifier: Programming Language :: Python :: Implementation :: PyPy
License-File: LICENSE
Provides-Extra: doc
Requires-Dist: sphinx; extra == "doc"
Requires-Dist: sphinx-rtd-theme; extra == "doc"
Provides-Extra: test
Requires-Dist: pytest; extra == "test"
Requires-Dist: mypy; extra == "test"
Requires-Dist: pycodestyle; extra == "test"
Requires-Dist: types-setuptools; extra == "test"
